indian_tax_fields/__init__.py
indian_tax_fields/constants.py
indian_tax_fields/gst/__init__.py
indian_tax_fields/gst/form_fields.py
indian_tax_fields/gst/model_fields.py
indian_tax_fields/gst/validators.py
indian_tax_fields/pan/__init__.py
indian_tax_fields/pan/form_fields.py
indian_tax_fields/pan/model_fields.py
indian_tax_fields/pan/validators.py
django_indian_tax_fields-0.1.0.dist-info/LICENSE
django_indian_tax_fields-0.1.0.dist-info/METADATA
django_indian_tax_fields-0.1.0.dist-info/WHEEL
django_indian_tax_fields-0.1.0.dist-info/RECORD
