Metadata-Version: 2.1
Name: django-indian-tax-fields
Version: 0.1.0
Summary: GST and PAN number field for django models.
Home-page: https://github.com/Mitrajeet-Golsangi/django-gst-field
License: MIT
Keywords: django,orm,python,gst,pan,indian,tax,fields
Author: Gandhar Pednekar
Author-email: gandhar.pednekar15@gmail.com
Maintainer: Mitrajeet Golsangi
Maintainer-email: mitrajeet.golsangi@gmail.com
Requires-Python: >=3.6,<4.0
Classifier: Development Status :: 5 - Production/Stable
Classifier: Framework :: Django
Classifier: Intended Audience :: Developers
Classifier: License :: OSI Approved :: MIT License
Classifier: Operating System :: OS Independent
Classifier: Programming Language :: Python
Classifier: Programming Language :: Python :: 3
Classifier: Programming Language :: Python :: 3.6
Classifier: Programming Language :: Python :: 3.7
Classifier: Programming Language :: Python :: 3.8
Classifier: Programming Language :: Python :: 3.9
Classifier: Programming Language :: Python :: 3.10
Classifier: Programming Language :: Python :: 3.11
Classifier: Programming Language :: Python :: 3.12
Classifier: Programming Language :: Python :: 3.13
Classifier: Programming Language :: Python :: Implementation :: CPython
Classifier: Topic :: Software Development :: Libraries :: Python Modules
Requires-Dist: django (>=3.0)
Project-URL: Repository, https://github.com/Mitrajeet-Golsangi/django-gst-field
